{"v":"5.12.1","fr":25,"ip":0,"op":23,"w":500,"h":500,"nm":"Sell-In Icon","ddd":1,"assets":[],"layers":[{"ddd":1,"ind":1,"ty":4,"nm":"Sell-In Icon","sr":1,"ks":{"o":{"k":[{"s":[0],"t":0,"i":{"x":[1],"y":[1]},"o":{"x":[0],"y":[0]}},{"s":[24.869],"t":1,"i":{"x":[1],"y":[1]},"o":{"x":[0],"y":[0]}},{"s":[45.229],"t":2,"i":{"x":[1],"y":[1]},"o":{"x":[0],"y":[0]}},{"s":[61.533],"t":3,"i":{"x":[1],"y":[1]},"o":{"x":[0],"y":[0]}},{"s":[74.23],"t":4,"i":{"x":[1],"y":[1]},"o":{"x":[0],"y":[0]}},{"s":[83.772],"t":5,"i":{"x":[1],"y":[1]},"o":{"x":[0],"y":[0]}},{"s":[90.609],"t":6,"i":{"x":[1],"y":[1]},"o":{"x":[0],"y":[0]}},{"s":[95.192],"t":7,"i":{"x":[1],"y":[1]},"o":{"x":[0],"y":[0]}},{"s":[97.971],"t":8,"i":{"x":[1],"y":[1]},"o":{"x":[0],"y":[0]}},{"s":[99.399],"t":9,"i":{"x":[1],"y":[1]},"o":{"x":[0],"y":[0]}},{"s":[99.925],"t":10,"i":{"x":[1],"y":[1]},"o":{"x":[0],"y":[0]}}]},"rx":{"a":0,"k":0,"ix":8},"ry":{"a":0,"k":0,"ix":9},"rz":{"k":[{"s":[-359],"t":0,"i":{"x":[1],"y":[1]},"o":{"x":[0],"y":[0]}},{"s":[-78.924],"t":1,"i":{"x":[1],"y":[1]},"o":{"x":[0],"y":[0]}},{"s":[65.842],"t":2,"i":{"x":[1],"y":[1]},"o":{"x":[0],"y":[0]}},{"s":[51.054],"t":3,"i":{"x":[1],"y":[1]},"o":{"x":[0],"y":[0]}},{"s":[4.007],"t":4,"i":{"x":[1],"y":[1]},"o":{"x":[0],"y":[0]}},{"s":[-12.536],"t":5,"i":{"x":[1],"y":[1]},"o":{"x":[0],"y":[0]}},{"s":[-6.634],"t":6,"i":{"x":[1],"y":[1]},"o":{"x":[0],"y":[0]}},{"s":[0.594],"t":7,"i":{"x":[1],"y":[1]},"o":{"x":[0],"y":[0]}},{"s":[2.119],"t":8,"i":{"x":[1],"y":[1]},"o":{"x":[0],"y":[0]}},{"s":[0.696],"t":9,"i":{"x":[1],"y":[1]},"o":{"x":[0],"y":[0]}},{"s":[-0.117],"t":10,"i":{"x":[1],"y":[1]},"o":{"x":[0],"y":[0]}},{"s":[0],"t":11,"i":{"x":[1],"y":[1]},"o":{"x":[0],"y":[0]}}]},"or":{"a":0,"k":[0,0,0],"ix":7},"p":{"s":true,"x":{"k":[{"s":[243.951],"t":0,"i":{"x":[1],"y":[1]},"o":{"x":[0],"y":[0]}},{"s":[243.951],"t":22,"i":{"x":[1],"y":[1]},"o":{"x":[0],"y":[0]}}]},"y":{"k":[{"s":[271.154],"t":0,"i":{"x":[1],"y":[1]},"o":{"x":[0],"y":[0]}},{"s":[271.154],"t":22,"i":{"x":[1],"y":[1]},"o":{"x":[0],"y":[0]}}]},"z":{"k":[{"s":[0],"t":0,"i":{"x":[1],"y":[1]},"o":{"x":[0],"y":[0]}},{"s":[0],"t":22,"i":{"x":[1],"y":[1]},"o":{"x":[0],"y":[0]}}]}},"a":{"a":0,"k":[713.195,819.215,0],"ix":1},"s":{"k":[{"s":[0.31,0.31,0.31],"t":0,"i":{"x":[1,1,1],"y":[1,1,1]},"o":{"x":[0,0,0],"y":[0,0,0]}},{"s":[0.93,0.93,0.93],"t":1,"i":{"x":[1,1,1],"y":[1,1,1]},"o":{"x":[0,0,0],"y":[0,0,0]}},{"s":[2.79,2.79,2.79],"t":2,"i":{"x":[1,1,1],"y":[1,1,1]},"o":{"x":[0,0,0],"y":[0,0,0]}},{"s":[5.889,5.889,5.889],"t":3,"i":{"x":[1,1,1],"y":[1,1,1]},"o":{"x":[0,0,0],"y":[0,0,0]}},{"s":[10.229,10.229,10.229],"t":4,"i":{"x":[1,1,1],"y":[1,1,1]},"o":{"x":[0,0,0],"y":[0,0,0]}},{"s":[15.379,15.379,15.379],"t":5,"i":{"x":[1,1,1],"y":[1,1,1]},"o":{"x":[0,0,0],"y":[0,0,0]}},{"s":[13.606,13.606,13.606],"t":6,"i":{"x":[1,1,1],"y":[1,1,1]},"o":{"x":[0,0,0],"y":[0,0,0]}},{"s":[13.073,13.073,13.073],"t":7,"i":{"x":[1,1,1],"y":[1,1,1]},"o":{"x":[0,0,0],"y":[0,0,0]}},{"s":[13.779,13.779,13.779],"t":8,"i":{"x":[1,1,1],"y":[1,1,1]},"o":{"x":[0,0,0],"y":[0,0,0]}},{"s":[15.417,15.417,15.417],"t":9,"i":{"x":[1,1,1],"y":[1,1,1]},"o":{"x":[0,0,0],"y":[0,0,0]}},{"s":[15.166,15.166,15.166],"t":10,"i":{"x":[1,1,1],"y":[1,1,1]},"o":{"x":[0,0,0],"y":[0,0,0]}},{"s":[15.5,15.5,15.5],"t":11,"i":{"x":[1,1,1],"y":[1,1,1]},"o":{"x":[0,0,0],"y":[0,0,0]}}]}},"ao":0,"ef":[{"ty":5,"nm":"AC IN [FQP] Controls","np":5,"mn":"Pseudo/MHAC PrCtrl FQP 4","ix":1,"en":1,"ef":[{"ty":3,"nm":"Position","mn":"Pseudo/MHAC PrCtrl FQP 4-0001","ix":1,"v":{"a":0,"k":[0,0],"ix":1}},{"ty":0,"nm":"Angle","mn":"Pseudo/MHAC PrCtrl FQP 4-0002","ix":2,"v":{"a":0,"k":-359,"ix":2}},{"ty":0,"nm":"Bounces","mn":"Pseudo/MHAC PrCtrl FQP 4-0003","ix":3,"v":{"a":0,"k":2,"ix":3}}]},{"ty":5,"nm":"AC IN [BCO] Controls","np":3,"mn":"Pseudo/MHAC PrCtrl BCO 4","ix":2,"en":1,"ef":[{"ty":0,"nm":"Scale","mn":"Pseudo/MHAC PrCtrl BCO 4-0001","ix":1,"v":{"a":0,"k":2,"ix":1}}]}],"shapes":[{"ty":"gr","it":[{"ind":0,"ty":"sh","ix":1,"ks":{"a":0,"k":{"i":[[0,-38.24],[26.5,0],[0,38.23],[-26.5,0]],"o":[[0,38.23],[-26.5,0],[0,-38.23],[26.5,0]],"v":[[-137.305,0.005],[-185.285,69.235],[-233.255,0.005],[-185.285,-69.225]],"c":true},"ix":2},"nm":"Path 1","mn":"ADBE Vector Shape - Group","hd":false},{"ind":1,"ty":"sh","ix":2,"ks":{"a":0,"k":{"i":[[0,42.95],[0,0],[38.97,11.24],[0,0],[0,-42.96],[0,0],[-38.97,11.24],[0,0]],"o":[[0,0],[0,-42.95],[0,0],[-38.97,-11.24],[0,0],[0,42.96],[0,0],[38.97,-11.24]],"v":[[307.045,522.785],[307.045,-522.785],[236.485,-620.915],[-236.485,-757.365],[-307.045,-699.945],[-307.045,699.945],[-236.485,757.365],[236.485,620.915]],"c":true},"ix":2},"nm":"Path 2","mn":"ADBE Vector Shape - Group","hd":false},{"ty":"mm","mm":1,"nm":"Merge Paths 1","mn":"ADBE Vector Filter - Merge","hd":false},{"ty":"fl","c":{"a":0,"k":[0.125490196078,0.250980392157,0.572549019608,1],"ix":4},"o":{"a":0,"k":100,"ix":5},"r":1,"bm":0,"nm":"Fill 1","mn":"ADBE Vector Graphic - Fill","hd":false},{"ty":"tr","p":{"a":0,"k":[1072.175,819.215],"ix":2},"a":{"a":0,"k":[0,0],"ix":1},"s":{"a":0,"k":[100,100],"ix":3},"r":{"a":0,"k":0,"ix":6},"o":{"a":0,"k":100,"ix":7},"sk":{"a":0,"k":0,"ix":4},"sa":{"a":0,"k":0,"ix":5},"nm":"Transform"}],"nm":"Group 1","np":4,"cix":2,"bm":0,"ix":1,"mn":"ADBE Vector Group","hd":false},{"ty":"gr","it":[{"ind":0,"ty":"sh","ix":1,"ks":{"a":0,"k":{"i":[[0,0],[0,0],[0,40.32],[0,0],[-40.31,0],[0,0],[0,0],[0,0],[0,0],[0,0]],"o":[[0,0],[-40.31,0],[0,0],[0,-40.31],[0,0],[0,0],[0,0],[0,0],[0,0],[0,0]],"v":[[94.045,631.895],[-20.945,631.895],[-94.045,558.785],[-94.045,-558.785],[-20.945,-631.895],[94.045,-631.895],[94.045,-543.545],[-5.695,-543.545],[-5.695,543.545],[94.045,543.545]],"c":true},"ix":2},"nm":"Path 1","mn":"ADBE Vector Shape - Group","hd":false},{"ty":"fl","c":{"a":0,"k":[0.125490196078,0.250980392157,0.572549019608,1],"ix":4},"o":{"a":0,"k":100,"ix":5},"r":1,"bm":0,"nm":"Fill 1","mn":"ADBE Vector Graphic - Fill","hd":false},{"ty":"tr","p":{"a":0,"k":[628.445,819.215],"ix":2},"a":{"a":0,"k":[0,0],"ix":1},"s":{"a":0,"k":[100,100],"ix":3},"r":{"a":0,"k":0,"ix":6},"o":{"a":0,"k":100,"ix":7},"sk":{"a":0,"k":0,"ix":4},"sa":{"a":0,"k":0,"ix":5},"nm":"Transform"}],"nm":"Group 2","np":2,"cix":2,"bm":0,"ix":2,"mn":"ADBE Vector Group","hd":false},{"ty":"gr","it":[{"ind":0,"ty":"sh","ix":1,"ks":{"a":0,"k":{"i":[[6.29,0],[0.26,-0.01],[4.82,-5.13],[0.2,-6.84],[-4.82,-5.12],[0,0],[0,0],[4.62,-4.91],[0,-7.26],[-4.62,-4.91],[-6.83,0],[0,0],[0,0],[-0.2,-6.84],[-4.42,-5.13],[-6.63,-0.22],[-0.24,0],[0,0],[-4.62,4.91],[0,0],[-1,2.99],[0,3.42],[1.01,2.99],[2.41,2.56],[0,0]],"o":[[-0.26,0],[-6.63,0.21],[-4.42,5.13],[-0.2,6.83],[0,0],[0,0],[-6.83,0],[-4.62,4.91],[0,7.26],[4.62,4.91],[0,0],[0,0],[-4.82,5.12],[0.2,6.83],[4.82,5.12],[0.25,0],[0,0],[6.27,-0.01],[0,0],[2.41,-2.56],[1,-2.99],[0,-3.42],[-1,-2.99],[0,0],[-4.63,-4.92]],"v":[[54.39,-142.575],[53.6,-142.565],[36.43,-134.555],[29.5,-116.615],[36.43,-98.675],[105.09,-25.635],[-163.53,-25.635],[-180.7,-18.265],[-187.63,-0.005],[-180.7,18.255],[-163.53,25.625],[105.1,25.625],[36.44,98.675],[29.51,116.615],[36.44,134.555],[53.61,142.565],[54.35,142.575],[54.45,142.575],[70.78,135.195],[181,17.935],[186.12,9.605],[187.63,-0.005],[186.12,-9.615],[181,-17.945],[70.77,-135.195]],"c":true},"ix":2},"nm":"Path 1","mn":"ADBE Vector Shape - Group","hd":false},{"ty":"fl","c":{"a":0,"k":[0.125490196078,0.250980392157,0.572549019608,1],"ix":4},"o":{"a":0,"k":100,"ix":5},"r":1,"bm":0,"nm":"Fill 1","mn":"ADBE Vector Graphic - Fill","hd":false},{"ty":"tr","p":{"a":0,"k":[234.8,819.215],"ix":2},"a":{"a":0,"k":[0,0],"ix":1},"s":{"a":0,"k":[100,100],"ix":3},"r":{"a":0,"k":0,"ix":6},"o":{"a":0,"k":100,"ix":7},"sk":{"a":0,"k":0,"ix":4},"sa":{"a":0,"k":0,"ix":5},"nm":"Transform"}],"nm":"Group 3","np":2,"cix":2,"bm":0,"ix":3,"mn":"ADBE Vector Group","hd":false}],"ip":0,"op":23,"st":-200,"ct":1,"bm":0}],"markers":[{"tm":-197,"cm":"Sales Activation Journey","dr":0},{"tm":-144,"cm":"ESSENTIALS","dr":0},{"tm":38,"cm":"SELL-IN","dr":0},{"tm":183,"cm":"SELL-THROUGH","dr":0},{"tm":408,"cm":"SELL-OUT","dr":0},{"tm":643,"cm":"FULL-SERVICE","dr":0}],"props":{}}